{
    "fluentMethods": true,
    "relationships": [
        {
            "relationshipName": "source",
            "otherEntityName": "source",
            "relationshipType": "many-to-one",
            "otherEntityField": "title"
        }
    ],
    "fields": [
        {
            "fieldName": "date",
            "fieldType": "ZonedDateTime"
        },
        {
            "fieldName": "title",
            "fieldType": "String"
        },
        {
            "fieldName": "desc",
            "fieldType": "byte[]",
            "fieldTypeBlobContent": "text"
        },
        {
            "fieldName": "stock",
            "fieldType": "String"
        }
    ],
    "changelogDate": "20170925025224",
    "dto": "mapstruct",
    "service": "serviceClass",
    "entityTableName": "info",
    "jpaMetamodelFiltering": true,
    "pagination": "pager",
    "microserviceName": "source",
    "searchEngine": "elasticsearch"
}
